mlflow_faculty/__init__.py
mlflow_faculty/artifacts.py
mlflow_faculty/context.py
mlflow_faculty/converters.py
mlflow_faculty/filter.py
mlflow_faculty/py23.py
mlflow_faculty/tracking.py
tests/__init__.py
tests/fixtures.py
tests/test_artifacts.py
tests/test_context.py
tests/test_converters.py
tests/test_filter.py
tests/test_py23.py
tests/test_tracking.py
mlflow_faculty-0.5.0.dist-info/LICENSE-2.0.txt
mlflow_faculty-0.5.0.dist-info/METADATA
mlflow_faculty-0.5.0.dist-info/WHEEL
mlflow_faculty-0.5.0.dist-info/entry_points.txt
mlflow_faculty-0.5.0.dist-info/top_level.txt
mlflow_faculty-0.5.0.dist-info/RECORD
