Metadata-Version: 2.1
Name: mlflow-faculty
Version: 0.5.0
Summary: MLflow plugin for the Faculty platform.
Home-page: https://faculty.ai/
Author: Faculty
Author-email: opensource@faculty.ai
License: Apache Software License
Platform: UNKNOWN
Requires-Dist: mlflow (~=1.7.0)
Requires-Dist: faculty (>=0.25.1)
Requires-Dist: six
Requires-Dist: pytz
Requires-Dist: sqlparse
Requires-Dist: enum34 ; python_version < "3.4"
